torrent_tracker_search/ClientBuilder.py
torrent_tracker_search/TorrentTrackerSearch.py
torrent_tracker_search/__init__.py
torrent_tracker_search/common/TorrentTracker.py
torrent_tracker_search/common/TrackerClient.py
torrent_tracker_search/common/TrackerRequestException.py
torrent_tracker_search/common/TrackerResponse.py
torrent_tracker_search/common/TrackerSearchNotFoundException.py
torrent_tracker_search/common/__init__.py
torrent_tracker_search/common/model/ISearchResultItem.py
torrent_tracker_search/common/model/ITorrentFile.py
torrent_tracker_search/common/model/ITorrentItem.py
torrent_tracker_search/common/model/__init__.py
torrent_tracker_search/source/__init__.py
torrent_tracker_search/source/nnmclub/NNMClubClient.py
torrent_tracker_search/source/nnmclub/NNMClubService.py
torrent_tracker_search/source/nnmclub/NNMClubURL.py
torrent_tracker_search/source/nnmclub/__init__.py
torrent_tracker_search/source/nnmclub/model/NNMClubAuthorLink.py
torrent_tracker_search/source/nnmclub/model/NNMClubForumLink.py
torrent_tracker_search/source/nnmclub/model/NNMClubSearchItem.py
torrent_tracker_search/source/nnmclub/model/NNMClubTopicLink.py
torrent_tracker_search/source/nnmclub/model/NNMClubTorrentFile.py
torrent_tracker_search/source/nnmclub/model/NNMClubTorrentItem.py
torrent_tracker_search/source/nnmclub/model/__init__.py
torrent_tracker_search/source/nnmclub/parser/NNMClubBBCodeParser.py
torrent_tracker_search/source/nnmclub/parser/NNMClubSearchParser.py
torrent_tracker_search/source/nnmclub/parser/NNMClubTorrentFilesParser.py
torrent_tracker_search/source/nnmclub/parser/NNMClubTorrentParser.py
torrent_tracker_search/source/nnmclub/parser/__init__.py
torrent_tracker_search/source/rutracker/RuTrackerClient.py
torrent_tracker_search/source/rutracker/RuTrackerService.py
torrent_tracker_search/source/rutracker/RuTrackerURL.py
torrent_tracker_search/source/rutracker/__init__.py
torrent_tracker_search/source/rutracker/model/RuTrackerAuthorLink.py
torrent_tracker_search-0.2.3.dist-info/LICENSE
torrent_tracker_search-0.2.3.dist-info/METADATA
torrent_tracker_search-0.2.3.dist-info/WHEEL
torrent_tracker_search-0.2.3.dist-info/RECORD
