Metadata-Version: 2.3
Name: torrent-tracker-search
Version: 0.2.3
Summary: Torrent Tracker Search Lib
License: MIT
Author: Николай Витальевич Никоноров
Author-email: nnv@bitt.moe
Requires-Python: >=3.10.16,<4.0.0
Classifier: License :: OSI Approved :: MIT License
Classifier: Programming Language :: Python :: 3
Classifier: Programming Language :: Python :: 3.11
Classifier: Programming Language :: Python :: 3.12
Classifier: Programming Language :: Python :: 3.13
Requires-Dist: aiohttp (==3.11.11)
Requires-Dist: beautifulsoup4 (==4.12.3)
Project-URL: Repository, https://gitlab.com/Bitnik212/torrent-tracker-search
